Metadata-Version: 2.1
Name: search-recommend
Version: 0.0.1
Summary: <Basic desc>
Author: neeraj03
Author-email: neerajjoshi9560562571@gmail.com
Classifier: Programming Language :: Python :: 3
Classifier: License :: OSI Approved :: MIT License
Classifier: Operating System :: OS Independent
License-File: LICENSE.txt
